lark/__init__.py
lark/detector.py
lark/model.py
lark/tokenizer.py
lark_ld-1.0.1.dist-info/licenses/LICENSE
lark_ld-1.0.1.dist-info/METADATA
lark_ld-1.0.1.dist-info/WHEEL
lark_ld-1.0.1.dist-info/entry_points.txt
lark_ld-1.0.1.dist-info/top_level.txt
lark_ld-1.0.1.dist-info/RECORD
